{
  "id": "11_Dimensionality_Reduction",
  "title": "11강 · 차원 축소 (Dimensionality Reduction: PCA, ICA)",
  "nodes": [
    {
      "name": "한 줄 정의 — 차원 축소란?",
      "children": [
        "고차원 데이터를 본질적 구조(intrinsic structure)를 보존하며 저차원으로 사영(projection)하는 기법",
        { "name": "PCA의 본질은?", "children": ["분산을 최대로 보존(= 사영 오차 최소)하는 직교 사영. 공분산행렬 S의 고유값분해로 풀림"] },
        { "name": "ICA의 본질은?", "children": ["비가우시안·통계적 독립을 가정해 신호를 분리"] },
        { "name": "⚠️ 자료 정합성 메모", "children": ["이 회차는 강의 녹취(STT) 누락 → 교재(11_Dimension.txt)를 단일 ground truth로 작성. 내용은 정확하나 교수 구두 강조는 미반영"] }
      ]
    },
    {
      "name": "핵심 개념 — 차원 축소 정의",
      "children": [
        { "name": "차원 축소란 무엇인가?", "children": ["고차원 공간의 데이터를 본질적 구조(intrinsic structure)를 보존하며 저차원으로 변환"] },
        { "name": "이상적으로 무엇을 반영?", "children": ["데이터의 고유 차원(intrinsic dimension)"] },
        { "name": "직관 예시", "children": ["3D 공간의 점들이 사실상 한 평면 위에 있으면 → 본질은 2차원. 중복(redundant) 정보를 버리고 단순 구조만 포착"] }
      ]
    },
    {
      "name": "왜 차원을 줄이는가 (고차원의 문제)",
      "children": [
        { "name": "문제 ①", "children": ["계산 비용 증가"] },
        { "name": "문제 ②", "children": ["많은 feature가 무관(irrelevant)하거나 잡음(noisy)"] },
        { "name": "문제 ③", "children": ["차원의 저주(curse of dimensionality)로 데이터가 희소(sparse)해짐"] }
      ]
    },
    {
      "name": "★ 차원의 저주 (Curse of Dimensionality)",
      "children": [
        { "name": "무슨 현상인가?", "children": ["차원(feature) 수가 늘수록 데이터가 점점 희소(sparse)해짐"] },
        { "name": "어떤 결과를 낳나?", "children": ["학습·추정·일반화(generalization)가 어려워짐"] },
        { "name": "보완하려면?", "children": ["지수적으로 더 많은 데이터(exponentially more data) 필요"] }
      ]
    },
    {
      "name": "핵심 과제 = 좋은 사영(projection) 찾기",
      "children": [
        "방법마다 \"유익한(informative) 사영\"의 정의·원리가 다름",
        { "name": "목적에 따른 선택 — 클래스 분리도 보존", "children": ["class separability 보존 → LDA"] },
        { "name": "목적에 따른 선택 — 분산 최대화", "children": ["variance 최대화 → PCA"] },
        { "name": "목적에 따른 선택 — 독립 성분 식별", "children": ["통계적으로 독립인 성분 식별 → ICA"] }
      ]
    },
    {
      "name": "★ 지도 vs 비지도 차원 축소 (중요 비교표)",
      "children": [
        { "name": "LDA (Linear Discriminant Analysis)", "children": ["학습 종류: 지도(supervised)", "목적/기준: 클래스 레이블 사용, 클래스 분리도 최대화"] },
        { "name": "PCA", "children": ["학습 종류: 비지도(unsupervised)", "목적/기준: 레이블 없음, 분산 보존(최대화)"] },
        { "name": "ICA", "children": ["학습 종류: 비지도(unsupervised)", "목적/기준: 레이블 없음, 통계적 독립 성분 분리"] },
        { "name": "본 장의 초점은?", "children": ["레이블이 없는 비지도 학습 맥락의 차원 축소 → PCA, ICA"] }
      ]
    },
    {
      "name": "PCA — 개요",
      "children": [
        { "name": "위상은?", "children": ["비지도 차원 축소에서 가장 중요·널리 쓰이는 기법"] },
        { "name": "핵심 아이디어는?", "children": ["분산 보존(preserving variance)"] },
        { "name": "★ 두 가지 동치(equivalent) 정의 — ① 최대 분산", "children": ["Maximum Variance: 사영된 데이터의 분산을 최대화하는, 저차원 선형 공간으로의 직교 사영(orthogonal projection)"] },
        { "name": "★ 두 가지 동치(equivalent) 정의 — ② 최소 오차", "children": ["Minimum Error: 데이터 점과 그 사영 사이의 평균제곱거리(사영 비용)를 최소화하는 선형 사영"] },
        { "name": "두 정의의 관계는?", "children": ["같은 알고리즘(공분산행렬 고유값분해)으로 귀결 → 동치"] }
      ]
    },
    {
      "name": "PCA · 최대 분산 정식화 (Maximum Variance Formulation)",
      "children": [
        { "name": "데이터 설정", "children": ["관측치 x⁽ⁿ⁾, n=1,…,N, 각 점은 D차원"] },
        { "name": "목표", "children": ["M < D 차원으로 사영하되 사영된 데이터의 분산을 최대화 (M은 우선 주어졌다고 가정)"] },
        { "name": "1차원 사영(M=1) — 방향 벡터 u₁", "children": ["단위벡터(크기가 아닌 방향에만 관심): u₁ᵀu₁ = 1"] },
        { "name": "각 점의 사영(스칼라)은?", "children": ["u₁ᵀx⁽ⁿ⁾"] },
        { "name": "사영 데이터의 평균은?", "children": ["u₁ᵀx̄, where 표본 평균 x̄ = (1/N)Σₙ x⁽ⁿ⁾"] },
        { "name": "사영된 데이터의 분산 → 공분산행렬 S로 표현", "children": [
          "(1/N)Σₙ(u₁ᵀx⁽ⁿ⁾ − u₁ᵀx̄)² = u₁ᵀ S u₁",
          { "name": "공분산행렬 S의 정의는?", "children": ["S = (1/N)Σₙ(x⁽ⁿ⁾ − x̄)(x⁽ⁿ⁾ − x̄)ᵀ"] }
        ]},
        { "name": "제약 최적화 — 왜 제약이 필요한가?", "children": ["그냥 u₁ᵀSu₁을 최대화하면 u₁를 키우는 것만으로 무한대 → 정규화 제약 u₁ᵀu₁=1 필요"] },
        { "name": "라그랑주 함수는?", "children": ["L = u₁ᵀ S u₁ + λ₁(1 − u₁ᵀu₁) — λ₁은 라그랑주 승수"] },
        { "name": "u₁에 대해 미분 → 0 하면?", "children": ["∂L/∂u₁ = 2Su₁ − 2λ₁u₁ = 0 ⇒ S u₁ = λ₁ u₁"] },
        { "name": "이 식이 의미하는 것은?", "children": ["u₁은 S의 고유벡터(eigenvector), λ₁은 고유값(eigenvalue)"] },
        { "name": "★ 분산 = 고유값 유도", "children": ["좌측에 u₁ᵀ 곱하고 u₁ᵀu₁=1 사용 → u₁ᵀ S u₁ = λ₁ ⇒ 분산 = 고유값 λ₁"] },
        { "name": "★ 그래서 무엇을 고르나?", "children": ["분산 최대화 = 가장 큰 고유값의 고유벡터 선택 → 이 고유벡터 = 제1 주성분(first principal component)"] },
        { "name": "추가 성분 & 직교성 — 왜 직교?", "children": ["다음 방향도 분산 최대 포착하되, 제약 없으면 제1성분과 겹침 → 이전 방향들과 직교(orthogonal)하도록 요구"] },
        { "name": "★ 직교성은 가정인가 결과인가?", "children": ["수학적으로 자연 발생: 대칭행렬 S의 서로 다른 고유값에 대응하는 고유벡터는 직교 (임의 부과 X)"] },
        { "name": "M차원 일반화 해는?", "children": ["S의 상위 M개 고유값 λ₁,…,λ_M에 대응하는 고유벡터 u₁,…,u_M. 이들이 주성분, 대응 고유값이 각 방향이 포착한 분산량을 정량화"] }
      ]
    },
    {
      "name": "PCA · 최소 오차 정식화 (Minimum Error Formulation)",
      "children": [
        { "name": "관점", "children": ["사영 오차(projection error) 최소화"] },
        { "name": "완전 정규직교 기저(complete orthonormal basis)", "children": [
          "uᵢ, i=1,…,D 에서 uᵢᵀuⱼ = δᵢⱼ (i=j면 1, 아니면 0)",
          { "name": "정규직교(orthonormal)란?", "children": ["서로 수직 + 단위 길이"] }
        ]},
        { "name": "각 점의 정확한 전개(= 좌표축 회전)", "children": ["x⁽ⁿ⁾ = Σᵢ₌₁ᴰ αᵢ⁽ⁿ⁾uᵢ, αᵢ⁽ⁿ⁾ = uᵢᵀx⁽ⁿ⁾"] },
        { "name": "저차원 근사식은?", "children": [
          "x̃⁽ⁿ⁾ = Σᵢ₌₁ᴹ zᵢ⁽ⁿ⁾uᵢ + Σᵢ₌ₘ₊₁ᴰ bᵢ uᵢ",
          { "name": "zᵢ⁽ⁿ⁾는 무엇?", "children": ["점마다 다른 저차원 좌표 (의미 있는 차이 포착)"] },
          { "name": "bᵢ는 무엇?", "children": ["모든 점에 공유되는 고정 상수 (D−M개 버려진 방향의 기여; 개별 변동성 모델링 X)"] }
        ]},
        { "name": "왜곡(distortion) J의 정의는?", "children": ["J = (1/N)Σₙ‖x⁽ⁿ⁾ − x̃⁽ⁿ⁾‖²"] },
        { "name": "동시 최적화가 어려운 이유 & 해법", "children": ["파라미터 3종 zᵢ⁽ⁿ⁾, bᵢ, uᵢ 동시 최적화는 어려움 → 2단계 분리"] },
        { "name": "2단계 분리 — 1단계", "children": ["기저 uᵢ 고정 → 좌표 최적화: zᵢ⁽ⁿ⁾ = x⁽ⁿ⁾ᵀuᵢ (i≤M), bᵢ = x̄ᵀuᵢ (i>M)"] },
        { "name": "2단계 분리 — 2단계", "children": ["정규직교 제약 하에 기저 uᵢ 최적화"] },
        { "name": "대입·정리한 왜곡은?", "children": ["J = Σᵢ₌ₘ₊₁ᴰ uᵢᵀ S uᵢ (정규직교성 덕에 제곱길이가 각 계수 제곱의 합으로 분해됨)"] },
        { "name": "다시 무엇으로 귀결?", "children": ["고유값 문제 S uᵢ = λᵢ uᵢ"] },
        { "name": "★ J 최소화 결론은?", "children": ["버리는 방향 = 가장 작은 D−M개 고유값 = 남기는 방향은 가장 큰 M개 고유값의 고유벡터 → 최대 분산 정식화와 동일 결론"] }
      ]
    },
    {
      "name": "★ PCA 알고리즘 절차 (시험 빈출)",
      "children": [
        { "name": "1단계", "children": ["데이터 평균 x̄ 계산 후 중심화(centering) (x⁽ⁿ⁾ − x̄)"] },
        { "name": "2단계", "children": ["공분산행렬 S = (1/N)Σ(x⁽ⁿ⁾−x̄)(x⁽ⁿ⁾−x̄)ᵀ 계산"] },
        { "name": "3단계", "children": ["S의 고유값분해: 고유값 λᵢ, 고유벡터 uᵢ"] },
        { "name": "4단계", "children": ["고유값을 내림차순 정렬, 상위 M개 고유벡터 선택 → 주성분"] },
        { "name": "5단계", "children": ["사영하여 M차원 표현 z⁽ⁿ⁾ 획득"] }
      ]
    },
    {
      "name": "PCA 응용 — 데이터 압축 / Eigenfaces",
      "children": [
        { "name": "고유벡터를 왜 이미지로 볼 수 있나?", "children": ["공분산행렬의 각 고유벡터는 원래 D차원 공간의 벡터 → 데이터와 같은 크기의 이미지로 시각화 가능"] },
        { "name": "예시 — 숫자(digits)", "children": ["상위 고유벡터들을 이미지로 표시, 고유값 스펙트럼은 내림차순 정렬"] },
        { "name": "예시 — 얼굴 이미지", "children": ["eigenfaces"] },
        { "name": "압축(인코딩) 수식은?", "children": ["zᵢ⁽ⁿ⁾ = (x⁽ⁿ⁾ − x̄)ᵀuᵢ — x⁽ⁿ⁾의 i번째 주성분 방향 좌표"] },
        { "name": "압축 표현은?", "children": ["z⁽ⁿ⁾ = (z₁⁽ⁿ⁾,…,z_M⁽ⁿ⁾)ᵀ ∈ ℝᴹ"] },
        { "name": "복원(디코딩) 수식은?", "children": ["x̂⁽ⁿ⁾ = x̄ + Σᵢ₌₁ᴹ zᵢ⁽ⁿ⁾uᵢ"] },
        { "name": "★ 복원 벡터의 차원은?", "children": ["원래(D)와 같지만 M개 성분 정보만 사용"] },
        { "name": "★ M의 트레이드오프는?", "children": ["M이 작을수록 압축률↑, 정보 손실↑ (예: M=1,10,50,250 → 클수록 원본에 근접)"] }
      ]
    },
    {
      "name": "ICA — 개요",
      "children": [
        { "name": "ICA 정의는?", "children": ["다변량 신호를 통계적으로 독립인 가법적(additive) 성분들로 분리하는 계산 기법"] },
        { "name": "주 용도는?", "children": ["source separation(신호원 분리). 추정 독립 성분 수를 원변수보다 적게 하면 feature 추출·차원 축소에도 사용 가능"] }
      ]
    },
    {
      "name": "★ ICA 핵심 가정과 PCA와의 차이",
      "children": [
        { "name": "중심 가정은?", "children": ["은닉 source들이 통계적으로 독립(statistically independent)"] },
        { "name": "★ 무상관(uncorrelated)이란?", "children": ["선형 관계 없음 (약한 조건)"] },
        { "name": "★ 독립(independent)이란?", "children": ["한 변수 값을 알아도 다른 변수에 대한 어떤 정보도 주지 않음 (강한 조건)"] },
        { "name": "★ 둘의 관계는?", "children": ["독립이면 무상관이지만, 무상관이라고 독립은 아님 (비선형 관계 가능). 독립이 더 강한 조건"] },
        { "name": "PCA vs ICA — PCA는?", "children": ["데이터를 직교(orthogonal) 성분으로 변환 → 무상관 보장. 단, 완전한 독립은 보장 X"] },
        { "name": "PCA vs ICA — ICA는?", "children": ["통계적 독립 성분 분리에 초점, 직교성 불요"] }
      ]
    },
    {
      "name": "★ ICA의 비가우시안(non-Gaussian) 가정",
      "children": [
        { "name": "무엇을 가정하나?", "children": ["ICA는 source가 비가우시안이라는 가정으로 분리"] },
        { "name": "가우시안 가정의 한계는?", "children": ["수학적으로 간단하지만, 실제 신호는 비가우시안 패턴이 많음"] },
        { "name": "★ source가 가우시안이면 왜 안 되나?", "children": ["가우시안의 선형결합도 가우시안 → 서로 다른 혼합이 통계적으로 유사해져 source를 유일하게 분리 불가"] },
        { "name": "비가우시안이면 왜 되나?", "children": ["비가우시안(예: 날카로운 peak 신호)은 혼합돼도 고유 특성 유지 → 분리 가능"] }
      ]
    },
    {
      "name": "칵테일 파티 문제 (Cocktail Party / Blind Source Separation)",
      "children": [
        { "name": "상황은?", "children": ["여러 사람이 동시에 말하고, 여러 마이크가 각각 다른 혼합을 녹음"] },
        { "name": "목표는?", "children": ["혼합 방식을 모른 채 원래의 독립적인 음성 신호들을 복원"] }
      ]
    },
    {
      "name": "ICA 수식 정식화",
      "children": [
        { "name": "선형 혼합 모델은?", "children": ["d차원 데이터 x ∈ ℝᵈ가 d개 독립 source s ∈ ℝᵈ의 선형 혼합: x = A s"] },
        { "name": "★ A(혼합행렬)란?", "children": ["미지의 d×d 혼합행렬(mixing matrix)"] },
        { "name": "★ 과제 & 분리행렬 W는?", "children": ["관측 x로부터 A와 s 복원. 분리행렬(unmixing matrix) W = A⁻¹ 찾기"] },
        { "name": "복원 수식은?", "children": ["s = W x, sᵢ⁽ⁿ⁾ = wᵢᵀx⁽ⁿ⁾ (wᵢᵀ = W의 i번째 행)"] },
        { "name": "독립 가정 → pdf는?", "children": ["결합 pdf = 주변 pdf의 곱: p(s) = Πᵢ₌₁ᵈ p(sᵢ)"] }
      ]
    },
    {
      "name": "ICA 추정 — 최대우도(Maximum Likelihood)",
      "children": [
        { "name": "왜 자코비안 보정이 필요한가?", "children": ["변수 변환 x → s 시 공간이 늘어남/줄어듦/회전/반전 → 자코비안(행렬식) 보정 필요"] },
        { "name": "det(W)의 의미 — >1", "children": ["공간 팽창(점들이 멀어짐) → 밀도 감소"] },
        { "name": "det(W)의 의미 — <1", "children": ["공간 수축 → 밀도 증가"] },
        { "name": "det(W)의 의미 — =1", "children": ["부피 보존"] },
        { "name": "밀도 변환식(전체 확률 1 유지)은?", "children": ["p(x) = p(s)·|det(W)| = Πᵢ₌₁ᵈ p_s(wᵢᵀx)·|det(W)|"] },
        { "name": "N개 관측의 로그우도는?", "children": ["L(W) = Σₙ Σᵢ log p_s(wᵢᵀx⁽ⁿ⁾) + log|det(W)|"] },
        { "name": "source 밀도 선택 — 왜 시그모이드 CDF?", "children": ["비가우시안이므로 비2차(non-quadratic) 함수로 pdf 근사. 흔한 선택: 시그모이드를 CDF로 사용"] },
        { "name": "시그모이드 CDF 수식은?", "children": ["p_s(sᵢ) ≈ g'(sᵢ), g(sᵢ) = 1/(1+e^{−sᵢ}), g'(sᵢ) = g(sᵢ)(1−g(sᵢ))"] },
        { "name": "g'의 특징은?", "children": ["시그모이드 미분 g'는 가우시안과 모양은 비슷하지만, 비가우시안 source를 근사하는 부드럽고 계산 쉬운 pdf 제공"] },
        { "name": "대입한 로그우도는?", "children": ["L(W) = Σₙ Σᵢ log g'(wᵢᵀx⁽ⁿ⁾) + log|det(W)|"] }
      ]
    },
    {
      "name": "ICA 학습 — 경사 상승(gradient ascent) 규칙",
      "children": [
        { "name": "그래디언트 성질 ① (시그모이드)", "children": ["∇_{wᵢ} log g'(wᵢᵀx⁽ⁿ⁾) = (1 − 2g(wᵢᵀx⁽ⁿ⁾))x⁽ⁿ⁾ (성질 g''/g' = 1−2g)"] },
        { "name": "그래디언트 성질 ② (행렬식)", "children": ["∇_W log|det W| = (W⁻¹)ᵀ = (Wᵀ)⁻¹"] },
        { "name": "★ 분리행렬 W 업데이트 규칙은?", "children": ["W ← W + α[(1/N)Σₙ x⁽ⁿ⁾(1 − 2g(Wx⁽ⁿ⁾))ᵀ + (Wᵀ)⁻¹]"] },
        { "name": "α, g의 의미는?", "children": ["α: 학습률, g: 비선형 함수(여기선 시그모이드 미분 — 비가우시안 포착)"] },
        { "name": "수렴 결과는?", "children": ["반복하면 W가 독립 source를 분리하는 해로 수렴"] }
      ]
    },
    {
      "name": "★ ICA의 본질적 모호성(ambiguity) — 시험 포인트",
      "children": [
        { "name": "전제", "children": ["혼합 관계 x=As를 완벽 복원해도 데이터만으로는 해결 불가한 두 가지"] },
        { "name": "★ 모호성 ① 순서(Permutation)", "children": ["A의 열을 바꾸면 source 순서만 바뀜 → 올바른 순서를 알 정보가 없음"] },
        { "name": "★ 모호성 ② 스케일(Scaling)", "children": ["source에 상수 곱하고 A의 해당 열을 같은 상수로 나누면 As 불변 (부호 포함 크기 식별 불가)"] },
        { "name": "실무에서는?", "children": ["절대 스케일·순서가 해석/유용성에 큰 영향 없어 대개 문제되지 않음"] }
      ]
    },
    {
      "name": "ICA 활용 예",
      "children": [
        { "name": "fMRI/EEG 분석", "children": ["기저 뇌 활동 신호 분리 및 아티팩트(artifact) 제거"] },
        { "name": "영상 분리", "children": ["원본 source 영상 ↔ 무작위 혼합 입력 ↔ ICA 복원 영상"] }
      ]
    },
    {
      "name": "★ 이 챕터 핵심 출제 포인트 (중요도순)",
      "children": [
        { "name": "출제 형식은?", "children": ["4지선다 개념 위주 / 수식 유도·계산 없음 / 이 챕터에서 4~5문제 예상. 기호가 보여도 '그 의미'만 묻는다. (이 회차는 STT 누락 → 교재 기반)"] },
        { "name": "★★★ PCA = 분산 보존(최대화) ⇔ 사영오차 최소화?", "children": ["두 정식화가 동치 → 같은 알고리즘(공분산행렬 고유값분해)으로 귀결. '서로 다른 해를 준다'가 함정"] },
        { "name": "★★★ 분산 = 고유값(λ) / 주성분 = 상위 λ 고유벡터?", "children": ["공분산행렬 S의 고유벡터=주성분 방향, 고유값 λ=그 방향이 포착한 분산량. '가장 큰 고유값 방향'이 분산 최대 보존"] },
        { "name": "★★★ PCA vs ICA — 무상관 vs 독립?", "children": ["PCA=무상관(2차 통계)·직교, ICA=통계적 독립(고차 통계)·직교 불요. 독립이 더 강한 조건, 무상관 ≠ 독립"] },
        { "name": "★★★ ICA 비가우시안(non-Gaussian) 가정 필수 + 이유?", "children": ["source가 가우시안이면 선형결합도 가우시안 → 혼합 구분 불가 → 분리 불가. 그래서 비가우시안 가정 필수"] },
        { "name": "★★ 지도 vs 비지도 — LDA vs PCA?", "children": ["LDA=지도(클래스 레이블 사용, 클래스 분리도 최대화), PCA·ICA=비지도(레이블 없음). 셋 다 선형 사영"] },
        { "name": "★★ 차원의 저주 / 차원 축소의 목적?", "children": ["차원↑ → 데이터 희소↑ → 일반화 어려움 → 지수적으로 더 많은 데이터 필요. 목적=본질 구조 보존하며 사영"] },
        { "name": "★★ ICA 모호성 2가지 — 순서·스케일?", "children": ["순서(permutation)·스케일(부호 포함 크기)은 데이터만으로 식별 불가. 단 실무상 대개 무해"] },
        { "name": "★ PCA 절차 / 직교성=가정 아닌 결과?", "children": ["중심화→공분산→고유값분해→상위 M. 중심화 필수, 직교성은 대칭행렬 고유벡터의 자연 발생 성질"] },
        { "name": "★ PCA 압축·복원(eigenfaces), M↓→압축↑·손실↑?", "children": ["복원 차원은 항상 D, 정보는 M개 성분만. M 작을수록 압축률↑·손실↑"] },
        { "name": "★ ICA 칵테일 파티 / 혼합행렬 A·분리행렬 W?", "children": ["칵테일 파티 = blind source separation. x=As(A=혼합행렬), W=A⁻¹로 s=Wx 복원"] }
      ]
    },
    {
      "name": "개념별 출제 각도 / 오답 포인트",
      "children": [
        { "name": "★★★ 1. PCA 두 정식화 동치 (최대 분산 ⇔ 최소 오차)", "children": [
          { "name": "의미?", "children": ["PCA는 ① 사영된 데이터의 분산을 최대화(Maximum Variance), ② 데이터-사영 간 평균제곱거리를 최소화(Minimum Error) 두 관점으로 정의되지만, 결국 같은 알고리즘(공분산행렬 고유값분해)으로 귀결. 분산을 가장 많이 남기는 방향 = 복원 오차가 가장 적은 방향(동전의 양면)"] },
          { "name": "오답 포인트?", "children": ["'두 정식화가 서로 다른 해를 준다' (X, 동치) / '최대 분산과 최소 오차는 무관하다' (X)"] },
          { "name": "예상 출제 각도?", "children": ["'PCA의 최대 분산과 최소 사영오차 정식화의 관계는?' → 동치, 같은 고유값 문제로 귀결"] }
        ]},
        { "name": "★★★ 2. 분산 = 고유값(λ), 주성분 = 상위 고유벡터", "children": [
          { "name": "의미?", "children": ["공분산행렬 S의 고유벡터 = 주성분 방향, 대응 고유값 λ = 그 방향이 포착한 분산의 양. 사영 분산 uᵀSu를 정규화 제약(uᵀu=1) 하에 라그랑주 최적화하면 Su=λu가 되고 그 분산값이 곧 λ. 가장 큰 고유값 상위 M개를 골라 M차원으로"] },
          { "name": "오답 포인트?", "children": ["'고유값 = 사영 오차' (X) / '고유값 = 데이터 개수/특징 수' (X). 고유값은 해당 주성분 방향의 분산"] },
          { "name": "예상 출제 각도?", "children": ["'공분산행렬의 고유값이 의미하는 것은?' → 해당 주성분 방향의 분산"] }
        ]},
        { "name": "★★★ 3. PCA vs ICA — 무상관 vs 통계적 독립", "children": [
          { "name": "의미?", "children": ["PCA = 직교(orthogonal) 성분으로 변환 → 무상관(uncorrelated) 보장, 2차 통계(분산/공분산)까지만, 가우시안 가정 OK, 완전 독립은 보장 안 함. ICA = 통계적 독립(고차 통계 포함) 성분 분리, 직교성 불요"] },
          { "name": "무상관 vs 독립?", "children": ["무상관 = 선형 관계 없음(약한 조건) / 독립 = 한 변수를 알아도 다른 변수에 대한 어떤 정보도 안 줌(강한 조건, 비선형까지 배제). 독립 ⇒ 무상관(참), 무상관 ⇏ 독립(거짓)"] },
          { "name": "오답 포인트?", "children": ["'무상관 = 독립' (X) / 'ICA는 직교 성분을 만든다' (X, 직교는 PCA) / 'PCA가 완전 독립을 보장한다' (X)"] },
          { "name": "예상 출제 각도?", "children": ["'ICA가 PCA와 다른 핵심은?' → 독립 vs 무상관, 직교성 요구 여부"] }
        ]},
        { "name": "★★★ 4. ICA의 비가우시안 가정과 이유", "children": [
          { "name": "의미?", "children": ["ICA는 은닉 source가 비가우시안(non-Gaussian)이라고 가정해야 성분을 분리 가능. 비가우시안(예: 날카로운 peak 신호)은 혼합돼도 고유 특성을 유지 → 분리 가능"] },
          { "name": "왜 가우시안이면 안 되나?", "children": ["가우시안의 선형결합도 또 가우시안 → 서로 다른 혼합(mixture)이 통계적으로 구분 안 됨 → source를 유일하게 분리 불가"] },
          { "name": "오답 포인트?", "children": ["'source가 가우시안이어도 ICA로 분리 가능' (X) / '비가우시안이면 분리 불가' (X, 반대)"] },
          { "name": "예상 출제 각도?", "children": ["'source가 가우시안이면 ICA로 분리할 수 있나?' → 불가. 이유: 가우시안 선형결합=가우시안"] }
        ]},
        { "name": "★★ 5. 지도 vs 비지도 (LDA vs PCA vs ICA)", "children": [
          { "name": "의미?", "children": ["LDA = 지도(supervised), 클래스 레이블 사용, 클래스 분리도(class separability) 최대화. PCA = 비지도, 분산 보존. ICA = 비지도, 통계적 독립 성분 분리. 셋 다 선형 사영 기반"] },
          { "name": "오답 포인트?", "children": ["'PCA는 레이블을 쓴다' (X, 레이블 쓰는 건 LDA) / 'ICA는 지도 학습' (X)"] },
          { "name": "예상 출제 각도?", "children": ["'다음 중 지도 차원축소는?' → LDA / 'PCA가 사용하는 정보는?' → 레이블 X, 분산 O"] }
        ]},
        { "name": "★★ 6. 차원의 저주 / 차원 축소의 목적", "children": [
          { "name": "의미?", "children": ["차원 축소 = 고차원 데이터를 본질적 구조(intrinsic structure)·고유 차원을 보존하며 저차원으로 사영, 중복·잡음 정보는 버림. 고차원의 문제 = 계산 비용↑, 무관·잡음 feature, 차원의 저주로 데이터 희소(sparse)"] },
          { "name": "차원의 저주란?", "children": ["차원↑ → 데이터 희소↑ → 학습·추정·일반화 어려움 → 보완하려면 지수적으로 더 많은 데이터 필요"] },
          { "name": "오답 포인트?", "children": ["'차원이 늘수록 데이터가 조밀해진다' (X, 희소해짐) / '차원 저주는 선형으로 데이터가 더 필요' (X, 지수적)"] },
          { "name": "예상 출제 각도?", "children": ["'차원의 저주가 의미하는 것은?' → 차원 증가 시 데이터 희소화/필요 데이터 지수 증가"] }
        ]},
        { "name": "★★ 7. ICA의 본질적 모호성 2가지", "children": [
          { "name": "의미?", "children": ["혼합 x=As를 완벽 복원해도 데이터만으로 해결 못 하는 두 가지. ① 순서 모호성(Permutation): source가 나오는 순서를 알 수 없음(A의 열 교환=순서만 바뀜). ② 스케일 모호성(Scaling): source의 크기·부호를 알 수 없음(source×상수, A 열÷상수 → As 불변)"] },
          { "name": "실무에서는?", "children": ["절대 스케일·순서는 해석에 큰 영향 없어 대개 문제 안 됨"] },
          { "name": "오답 포인트?", "children": ["'ICA는 source의 순서·스케일까지 복원한다' (X) / 모호성을 '독립성', 'source 개수'로 (X)"] },
          { "name": "예상 출제 각도?", "children": ["'ICA가 데이터만으로 식별 못 하는 것은?' → 순서·스케일(부호/크기)"] }
        ]},
        { "name": "★ 8. PCA 절차 + 직교성은 결과", "children": [
          { "name": "의미?", "children": ["절차: ① 평균 계산 후 중심화(centering) → ② 공분산행렬 S 계산 → ③ 고유값분해 → ④ 고유값 내림차순, 상위 M개 고유벡터 선택 → ⑤ M차원으로 사영. 중심화 필수(공분산·사영 계수 모두 x−x̄ 사용)"] },
          { "name": "직교성?", "children": ["대칭행렬(공분산행렬)의 서로 다른 고유값에 대응하는 고유벡터는 자동으로 직교 → 임의로 부과한 가정이 아니라 수학적 결과"] },
          { "name": "오답 포인트?", "children": ["'주성분 직교성은 인위적 가정이다' (X, 자연 발생) / '중심화 없이 PCA 가능' (X에 가까움, 중심화는 전제)"] },
          { "name": "예상 출제 각도?", "children": ["'PCA에서 주성분들이 직교인 이유?' → 공분산행렬이 대칭행렬이라서. '필수 전처리?' → 중심화"] }
        ]},
        { "name": "★ 9. PCA 압축/복원 (eigenfaces)", "children": [
          { "name": "의미?", "children": ["고유벡터는 원래 D차원 벡터 → 이미지로 시각화 가능(얼굴=eigenfaces). 압축(인코딩) zᵢ=(x−x̄)ᵀuᵢ = i번째 주성분 좌표, 압축표현은 M차원 z. 복원(디코딩) x̂=x̄+Σzᵢuᵢ"] },
          { "name": "트레이드오프?", "children": ["복원 차원은 항상 원래 D지만 정보는 M개 성분만. M이 작을수록 압축률↑·정보 손실↑(M=1,10,50,250 → 클수록 원본에 근접)"] },
          { "name": "오답 포인트?", "children": ["'복원 벡터의 차원이 M이다' (X, 항상 D) / 'M을 줄이면 손실이 준다' (X, 손실 증가)"] },
          { "name": "예상 출제 각도?", "children": ["'M을 줄이면?' → 압축률↑·손실↑ / '복원 벡터의 차원은?' → D"] }
        ]},
        { "name": "★ 10. ICA 칵테일 파티 / A·W의 의미", "children": [
          { "name": "의미?", "children": ["칵테일 파티 문제 = blind source separation. 여러 화자 + 여러 마이크(각기 다른 혼합) → 혼합 방식을 모른 채 원래 독립 신호 복원. x=As(A=미지의 혼합행렬 mixing matrix), 목표는 분리행렬(unmixing) W=A⁻¹ 찾아 s=Wx. 독립 가정 → p(s)=Πp(sᵢ)"] },
          { "name": "오답 포인트?", "children": ["A를 분리행렬로, W를 혼합행렬로 뒤바꾸기 (X) / '혼합 방식(A)을 미리 안다' (X, blind)"] },
          { "name": "예상 출제 각도?", "children": ["'혼합행렬 A / 분리행렬 W가 뜻하는 것?', '칵테일 파티가 예시하는 것?' → blind source separation"] }
        ]}
      ]
    },
    {
      "name": "⚠️ 객관식 함정 포인트",
      "children": [
        { "name": "무상관 = 독립 (X)", "children": ["독립 ⇒ 무상관은 맞지만 역은 거짓. ICA=독립, PCA=무상관"] },
        { "name": "PCA 두 정식화가 다른 결과를 준다 (X)", "children": ["동치 → 같은 고유값 문제로 귀결"] },
        { "name": "고유값 = 사영 오차 / 데이터 수 (X)", "children": ["고유값 = 해당 주성분 방향의 분산"] },
        { "name": "주성분 직교성은 인위적 가정이다 (X)", "children": ["대칭(공분산)행렬 고유벡터의 자연 발생 성질"] },
        { "name": "PCA는 레이블을 쓴다 (X)", "children": ["PCA·ICA는 비지도. 레이블 쓰는 건 LDA"] },
        { "name": "ICA는 직교 성분을 만든다 (X)", "children": ["직교성 불필요. 직교/무상관은 PCA"] },
        { "name": "source가 가우시안이어도 ICA로 분리 가능 (X)", "children": ["가우시안 선형결합=가우시안 → 분리 불가"] },
        { "name": "PCA 복원 벡터의 차원은 M이다 (X)", "children": ["차원은 항상 D, 정보만 M개 성분"] },
        { "name": "ICA는 source의 순서·스케일까지 복원한다 (X)", "children": ["순서·스케일(부호 포함)은 식별 불가"] },
        { "name": "중심화 없이 PCA 가능 (X에 가까움)", "children": ["평균 제거(centering)는 공분산·사영 계산의 전제"] },
        { "name": "상위 vs 하위 고유값", "children": ["남기는 건 큰 M개, 버리는 건 작은 D−M개 (최소오차 정식화에서 헷갈리기 쉬움)"] },
        { "name": "차원의 저주 — 데이터 조밀화? (X)", "children": ["차원↑ → 데이터 희소↑, 필요 데이터는 지수적으로 증가"] }
      ]
    },
    {
      "name": "★ 시험 포인트 / 자주 헷갈리는 점",
      "children": [
        { "name": "PCA 두 정식화 동치", "children": ["\"최대 분산\" = \"최소 사영(복원) 오차\". 결국 같은 알고리즘(공분산행렬 고유값분해)"] },
        { "name": "PCA 핵심 수식 흐름", "children": ["분산 = uᵀSu → 정규화 제약 uᵀu=1 → 라그랑주 → Su=λu(고유값 문제) → 분산 = 고유값 λ"] },
        { "name": "분산 = 고유값", "children": ["가장 큰 고유값 방향이 분산을 가장 많이 보존. 상위 M개 선택"] },
        { "name": "직교성은 가정이 아니라 결과", "children": ["대칭행렬(공분산행렬)의 서로 다른 고유값에 대응하는 고유벡터는 자동으로 직교"] },
        { "name": "중심화(평균 제거)는 필수 전처리", "children": ["공분산행렬·사영 계수 계산 모두 x−x̄ 사용"] },
        { "name": "M 줄이면", "children": ["압축률↑·정보손실↑ (복원 차원은 항상 D지만 정보는 M개 성분만)"] },
        { "name": "PCA vs ICA (단골 비교)", "children": ["PCA → 직교/무상관, 2차 통계(분산)까지만, 가우시안 가정 OK. ICA → 통계적 독립(고차 통계), 비가우시안 가정 필수, 직교 불요. 무상관 ≠ 독립(독립이 더 강함)"] },
        { "name": "ICA에 가우시안이 안 되는 이유", "children": ["가우시안의 선형결합도 가우시안 → 혼합 구분 불가 → 분리 불가능"] },
        { "name": "ICA 모호성 2가지", "children": ["순서(permutation), 스케일(scaling). 부호/크기/순서는 식별 불가하지만 실무상 무해"] },
        { "name": "LDA vs PCA 혼동 주의", "children": ["LDA는 지도(클래스 분리도), PCA는 비지도(분산). 둘 다 선형 사영"] },
        { "name": "차원의 저주", "children": ["차원↑ → 데이터 희소↑ → 일반화 어려움 → 지수적으로 더 많은 데이터 필요"] },
        { "name": "자코비안 보정", "children": ["ICA 우도에서 |det(W)| 항을 빠뜨리지 말 것 (변수 변환에 따른 밀도 보정)"] },
        { "name": "ICA 학습", "children": ["시그모이드 CDF로 source 밀도 근사 → 로그우도 경사 상승 → W 업데이트"] }
      ]
    },
    {
      "name": "✅ 셀프 체크 (반드시 답할 수 있어야 함)",
      "children": [
        { "name": "Q1. PCA의 '최대 분산'과 '최소 사영오차' 정식화가 동치인 이유를 한 문장으로?", "children": ["남기는 분산↑ = 버리는 복원오차↓ (동전의 양면). 둘 다 공분산행렬 고유값분해로 귀결"] },
        { "name": "Q2. 공분산행렬의 고유값 λ가 의미하는 것은? 주성분은 어떤 고유벡터로 고르나?", "children": ["λ = 해당 주성분 방향이 포착한 분산량 / 큰 λ 상위 M개의 고유벡터"] },
        { "name": "Q3. 무상관과 독립의 차이, 그리고 PCA·ICA가 각각 보장하는 것은?", "children": ["무상관 = 선형 무관(약함) vs 독립 = 모든(비선형 포함) 정보 무관(강함) / PCA=무상관, ICA=독립"] },
        { "name": "Q4. ICA에서 source가 가우시안이면 안 되는 이유는?", "children": ["가우시안의 선형결합도 가우시안 → 서로 다른 혼합이 통계적으로 구분 불가 → 유일 분리 불가"] },
        { "name": "Q5. ICA가 데이터만으로 식별할 수 없는 두 가지 모호성은?", "children": ["순서(permutation), 스케일(scaling, 부호 포함). 단 실무상 대개 무해"] }
      ]
    }
  ]
}
